mypy_json_report/__init__.py
mypy_json_report/__main__.py
mypy_json_report/cli.py
mypy_json_report/exit_codes.py
mypy_json_report/parse.py
mypy_json_report-1.3.0.dist-info/LICENSE
mypy_json_report-1.3.0.dist-info/METADATA
mypy_json_report-1.3.0.dist-info/WHEEL
mypy_json_report-1.3.0.dist-info/entry_points.txt
mypy_json_report-1.3.0.dist-info/RECORD
