Metadata-Version: 2.3
Name: mypy-json-report
Version: 1.3.0
Summary: Generate a JSON report from your mypy output
License: Apache-2.0
Author: Charlie Denton
Author-email: charlie@meshy.co.uk
Requires-Python: >= 3.9
Classifier: Intended Audience :: Developers
Classifier: License :: OSI Approved :: Apache Software License
Classifier: Programming Language :: Python
Classifier: Programming Language :: Python :: 3
Classifier: Programming Language :: Python :: 3 :: Only
Classifier: Programming Language :: Python :: 3.9
Classifier: Programming Language :: Python :: 3.10
Classifier: Programming Language :: Python :: 3.11
Classifier: Programming Language :: Python :: 3.12
Classifier: Programming Language :: Python :: 3.13
Classifier: Programming Language :: Python :: 3.14
Classifier: Topic :: Software Development
Classifier: Topic :: Utilities
Project-URL: Source, https://github.com/memrise/mypy-json-report
